pdf_pagemerge/__init__.py
pdf_pagemerge/pdf_pagemerge.py
pdf_pagemerge-0.0.3.dist-info/METADATA
pdf_pagemerge-0.0.3.dist-info/WHEEL
pdf_pagemerge-0.0.3.dist-info/entry_points.txt
pdf_pagemerge-0.0.3.dist-info/licenses/LICENSE
pdf_pagemerge-0.0.3.dist-info/RECORD
