Metadata-Version: 2.4
Name: pdf-pagemerge
Version: 0.0.3
Summary: Tool for encased python script environment.
Project-URL: Homepage, https://github.com/nanigashi-uji/pdf-pagemerge
Author-email: Nanigashi Uji <53845049+nanigashi-uji@users.noreply.github.com>, Nanigashi Uji <4423013-nanigashi_uji@users.noreply.gitlab.com>
Maintainer-email: Nanigashi Uji <53845049+nanigashi-uji@users.noreply.github.com>, Nanigashi Uji <4423013-nanigashi_uji@users.noreply.gitlab.com>
License: BSD 3-Clause License
License-File: LICENSE
Keywords: development,pdf,template
Classifier: Development Status :: 2 - Pre-Alpha
Classifier: Programming Language :: Python
Classifier: Programming Language :: Python :: 3
Classifier: Programming Language :: Python :: 3.9
Classifier: Programming Language :: Python :: 3.10
Classifier: Programming Language :: Python :: 3.11
Classifier: Programming Language :: Python :: 3.12
Classifier: Programming Language :: Python :: 3.13
Classifier: Topic :: Software Development
Classifier: Topic :: Utilities
Requires-Python: >=3.9
Requires-Dist: pypdf
